unislate.py
Unislate-0.1.1.dist-info/METADATA
Unislate-0.1.1.dist-info/WHEEL
Unislate-0.1.1.dist-info/entry_points.txt
Unislate-0.1.1.dist-info/top_level.txt
Unislate-0.1.1.dist-info/RECORD
