Metadata-Version: 2.1
Name: Unislate
Version: 0.1.1
Summary: Минималистичный консольный редактор с подсветкой синтаксиса
Home-page: https://github.com/qwez-source/unislate
Author: Qwez
Classifier: Programming Language :: Python :: 3
Classifier: License :: OSI Approved :: MIT License
Classifier: Operating System :: OS Independent
Requires-Dist: windows-curses
